{
  "lastUpdated": "2026-01-27T23:17:24.455Z",
  "PTGC": {
    "volume": {
      "vol7d": 318063.41400895355,
      "vol30d": 1346384.720330161,
      "vol90d": 5048383.315161991
    },
    "liquidity": 2811845.9855,
    "transactions": {
      "buys": 269,
      "sells": 140,
      "total": 409,
      "buyVolume": 13364.051240760211,
      "sellVolume": 11828.17375839622
    },
    "holders": 17048,
    "tokensInLP": 10245015040.1856,
    "poolCount": 20,
    "priceChanges": {
      "h24": 1.30642,
      "d7": -14.68303,
      "d30": 11.67051,
      "d60": -9.21032,
      "d90": -74.79482,
      "d200": -74.79482,
      "d1y": -86.91716
    }
  },
  "UFO": {
    "volume": {
      "vol7d": 150493.11651319248,
      "vol30d": 417650.9801148011,
      "vol90d": 2121614.308738877
    },
    "liquidity": 2474840.6355,
    "transactions": {
      "buys": 69,
      "sells": 38,
      "total": 107,
      "buyVolume": 4429.499903654869,
      "sellVolume": 2912.9861911365592
    },
    "holders": 6331,
    "tokensInLP": 221187786268.549,
    "poolCount": 20,
    "priceChanges": {
      "h24": 0.23263,
      "d7": -4.32237,
      "d30": -4.94339,
      "d60": -28.3886,
      "d90": -73.87678,
      "d200": -73.87678,
      "d1y": -93.69564
    }
  },
  "rhCores": {
    "WPLS": {
      "address": "0xa1077a294dde1b09bb078844df40758a5d0f9a27",
      "priceChanges": {
        "h24": 1.13002,
        "d7": -1.21754,
        "d30": -5.17491,
        "d60": -28.79278,
        "d90": -55.35416,
        "d200": -55.35416,
        "d1y": -71.31874
      }
    },
    "PLSX": {
      "address": "0x95b303987a60c71504d99aa1b13b4da07b0790ab",
      "priceChanges": {
        "h24": 2.35152,
        "d7": 7.00521,
        "d30": -6.4508,
        "d60": -9.16305,
        "d90": -51.96421,
        "d200": -51.96421,
        "d1y": -65.25529
      }
    },
    "INC": {
      "address": "0x2fa878ab3f87cc1c9737fc071108f904c0b0c95d",
      "priceChanges": {
        "h24": 1.68665,
        "d7": 3.97989,
        "d30": -7.90524,
        "d60": -20.51022,
        "d90": -67.11683,
        "d200": -67.11683,
        "d1y": -66.80218
      }
    },
    "HEX": {
      "address": "0x2b591e99afe9f32eaa6214f7b7629768c40eeb39",
      "priceChanges": {
        "h24": 4.8255,
        "d7": 2.59654,
        "d30": -10.74927,
        "d60": -38.57807,
        "d90": -60.90677,
        "d200": -60.90677,
        "d1y": -82.80704
      }
    },
    "EHEX": {
      "address": "0x57fde0a71132198bbec939b98976993d8d89d225",
      "priceChanges": {
        "h24": 0.64464,
        "d7": 0.00295,
        "d30": -11.05003,
        "d60": -32.88268,
        "d90": -58.76955,
        "d200": -58.76955,
        "d1y": -73.03756
      }
    }
  }
}