{
  "lastUpdated": "2026-01-24T21:14:13.689Z",
  "PTGC": {
    "volume": {
      "vol7d": 299197.599572155,
      "vol30d": 1353083.004868541,
      "vol90d": 5211289.404823518
    },
    "liquidity": 2699433.9436000003,
    "transactions": {
      "buys": 652,
      "sells": 405,
      "total": 1057,
      "buyVolume": 33305.39926450242,
      "sellVolume": 49906.332910144185
    },
    "holders": 17042,
    "tokensInLP": 10318107197,
    "poolCount": 20,
    "priceChanges": {
      "h24": -3.94187,
      "d7": -25.03153,
      "d30": -1.48749,
      "d60": -3.59696,
      "d90": -64.27388,
      "d200": -64.27388,
      "d1y": -85.3882
    }
  },
  "UFO": {
    "volume": {
      "vol7d": 120559.9598680791,
      "vol30d": 410684.8940222704,
      "vol90d": 2258560.264968001
    },
    "liquidity": 2571956.1442000004,
    "transactions": {
      "buys": 256,
      "sells": 215,
      "total": 471,
      "buyVolume": 33795.588798736935,
      "sellVolume": 41952.025324304734
    },
    "holders": 6334,
    "tokensInLP": 221158130307,
    "poolCount": 20,
    "priceChanges": {
      "h24": 1.37036,
      "d7": -14.59458,
      "d30": -1.69443,
      "d60": -23.22062,
      "d90": -64.63519,
      "d200": -64.63519,
      "d1y": -92.1791
    }
  },
  "rhCores": {
    "WPLS": {
      "address": "0xa1077a294dde1b09bb078844df40758a5d0f9a27",
      "priceChanges": {
        "h24": 2.60165,
        "d7": -10.71271,
        "d30": -5.2651,
        "d60": -20.88046,
        "d90": -43.40796,
        "d200": -43.40796,
        "d1y": -71.55112
      }
    },
    "PLSX": {
      "address": "0x95b303987a60c71504d99aa1b13b4da07b0790ab",
      "priceChanges": {
        "h24": 14.38623,
        "d7": -0.40283,
        "d30": 1.1253,
        "d60": 0.9456,
        "d90": -35.38036,
        "d200": -35.38036,
        "d1y": -64.86802
      }
    },
    "INC": {
      "address": "0x2fa878ab3f87cc1c9737fc071108f904c0b0c95d",
      "priceChanges": {
        "h24": 4.99932,
        "d7": -2.72908,
        "d30": -5.64294,
        "d60": -13.56465,
        "d90": -58.19925,
        "d200": -58.19925,
        "d1y": -67.71001
      }
    },
    "HEX": {
      "address": "0x2b591e99afe9f32eaa6214f7b7629768c40eeb39",
      "priceChanges": {
        "h24": -2.63439,
        "d7": -14.96368,
        "d30": -14.45518,
        "d60": -38.18569,
        "d90": -56.20652,
        "d200": -56.20652,
        "d1y": -84.22009
      }
    },
    "EHEX": {
      "address": "0x57fde0a71132198bbec939b98976993d8d89d225",
      "priceChanges": {
        "h24": -7.34174,
        "d7": -10.02144,
        "d30": -14.58756,
        "d60": -33.264,
        "d90": -54.16143,
        "d200": -54.16143,
        "d1y": -74.14887
      }
    }
  }
}