{
  "lastUpdated": "2026-01-16T09:47:04.736Z",
  "PTGC": {
    "volume": {
      "vol7d": 348089.0513322319,
      "vol30d": 1386979.024635848,
      "vol90d": 5521943.193261646
    },
    "liquidity": 2692864.4613,
    "transactions": {
      "buys": 571,
      "sells": 282,
      "total": 853,
      "buyVolume": 29708.83097162364,
      "sellVolume": 46181.347373914396
    },
    "holders": 17012,
    "tokensInLP": 9878876226,
    "poolCount": 20
  },
  "UFO": {
    "volume": {
      "vol7d": 40953.3655085876,
      "vol30d": 289095.91804962157,
      "vol90d": 1666174.4779075456
    },
    "liquidity": 2413530.4311000006,
    "transactions": {
      "buys": 104,
      "sells": 73,
      "total": 177,
      "buyVolume": 1951.3482608033635,
      "sellVolume": 1319.01214532161
    },
    "holders": 6335,
    "tokensInLP": 166177965408,
    "poolCount": 20
  }
}