{
  "lastUpdated": "2026-01-26T18:28:08.617Z",
  "PTGC": {
    "volume": {
      "vol7d": 339695.54249590385,
      "vol30d": 1410316.958926218,
      "vol90d": 5216519.888828001
    },
    "liquidity": 1935341.6556,
    "transactions": {
      "buys": 251,
      "sells": 226,
      "total": 477,
      "buyVolume": 19571.77653117434,
      "sellVolume": 13643.235808661937
    },
    "holders": 17050,
    "tokensInLP": 10168223296.6445,
    "poolCount": 20,
    "priceChanges": {
      "h24": -0.21885,
      "d7": -20.56228,
      "d30": -1.33318,
      "d60": -15.4849,
      "d90": -68.26101,
      "d200": -68.26101,
      "d1y": -88.20887
    }
  },
  "UFO": {
    "volume": {
      "vol7d": 138399.41590066583,
      "vol30d": 405946.1983488344,
      "vol90d": 2138213.3275047312
    },
    "liquidity": 2364881.9707,
    "transactions": {
      "buys": 81,
      "sells": 87,
      "total": 168,
      "buyVolume": 3131.8856156367033,
      "sellVolume": 6749.278088443531
    },
    "holders": 6333,
    "tokensInLP": 221133059171.5164,
    "poolCount": 20,
    "priceChanges": {
      "h24": -2.13059,
      "d7": -12.82844,
      "d30": -12.91239,
      "d60": -33.76984,
      "d90": -69.1053,
      "d200": -69.1053,
      "d1y": -94.56313
    }
  },
  "rhCores": {
    "WPLS": {
      "address": "0xa1077a294dde1b09bb078844df40758a5d0f9a27",
      "priceChanges": {
        "h24": -3.39606,
        "d7": -11.62421,
        "d30": -12.88248,
        "d60": -32.95619,
        "d90": -50.86672,
        "d200": -50.86672,
        "d1y": -75.12282
      }
    },
    "PLSX": {
      "address": "0x95b303987a60c71504d99aa1b13b4da07b0790ab",
      "priceChanges": {
        "h24": -2.14629,
        "d7": -5.22752,
        "d30": -16.8183,
        "d60": -17.11518,
        "d90": -45.05697,
        "d200": -45.05697,
        "d1y": -70.99844
      }
    },
    "INC": {
      "address": "0x2fa878ab3f87cc1c9737fc071108f904c0b0c95d",
      "priceChanges": {
        "h24": -4.08666,
        "d7": -5.27941,
        "d30": -18.2669,
        "d60": -24.99483,
        "d90": -63.4721,
        "d200": -63.4721,
        "d1y": -73.0793
      }
    },
    "HEX": {
      "address": "0x2b591e99afe9f32eaa6214f7b7629768c40eeb39",
      "priceChanges": {
        "h24": -1.4121,
        "d7": -11.07574,
        "d30": -18.54096,
        "d60": -43.48684,
        "d90": -58.36156,
        "d200": -58.36156,
        "d1y": -86.05467
      }
    },
    "EHEX": {
      "address": "0x57fde0a71132198bbec939b98976993d8d89d225",
      "priceChanges": {
        "h24": -2.60279,
        "d7": -7.06706,
        "d30": -16.26135,
        "d60": -38.69879,
        "d90": -57.08199,
        "d200": -57.08199,
        "d1y": -76.80801
      }
    }
  }
}