{
  "lastUpdated": "2026-01-20T03:17:01.130Z",
  "PTGC": {
    "volume": {
      "vol7d": 224131.74514135122,
      "vol30d": 1349267.7691367688,
      "vol90d": 5274835.66217821
    },
    "liquidity": 1653673.4755000002,
    "transactions": {
      "buys": 354,
      "sells": 251,
      "total": 605,
      "buyVolume": 27573.410320323805,
      "sellVolume": 19858.607638263045
    },
    "holders": 17023,
    "tokensInLP": 9798025150.0817,
    "poolCount": 20,
    "priceChanges": {
      "h24": -2.9968,
      "d7": -14.18209,
      "d30": 0.59473,
      "d60": 20.58913,
      "d90": -55.04483,
      "d200": -55.04483,
      "d1y": -74.86591
    }
  },
  "UFO": {
    "volume": {
      "vol7d": 30628.790733520393,
      "vol30d": 278234.77450772485,
      "vol90d": 1740019.0253011489
    },
    "liquidity": 2093176.6706999997,
    "transactions": {
      "buys": 51,
      "sells": 100,
      "total": 151,
      "buyVolume": 2013.791020450469,
      "sellVolume": 2168.951759219283
    },
    "holders": 6336,
    "tokensInLP": 186425597685,
    "poolCount": 20,
    "priceChanges": {
      "h24": -5.77112,
      "d7": -12.39925,
      "d30": -14.21963,
      "d60": -21.28855,
      "d90": -61.63532,
      "d200": -61.63532,
      "d1y": -87.488
    }
  },
  "rhCores": {
    "WPLS": {
      "address": "0xa1077a294dde1b09bb078844df40758a5d0f9a27",
      "priceChanges": {
        "h24": -6.30376,
        "d7": -7.91826,
        "d30": -15.02744,
        "d60": -21.30006,
        "d90": -39.81292,
        "d200": -39.81292,
        "d1y": -67.47355
      }
    },
    "PLSX": {
      "address": "0x95b303987a60c71504d99aa1b13b4da07b0790ab",
      "priceChanges": {
        "h24": -6.14175,
        "d7": -11.47273,
        "d30": -20.66782,
        "d60": -7.08047,
        "d90": -39.37674,
        "d200": -39.37674,
        "d1y": -61.9405
      }
    },
    "INC": {
      "address": "0x2fa878ab3f87cc1c9737fc071108f904c0b0c95d",
      "priceChanges": {
        "h24": -4.12692,
        "d7": -9.28742,
        "d30": -20.94203,
        "d60": -28.77258,
        "d90": -62.36536,
        "d200": -62.36536,
        "d1y": -65.91922
      }
    },
    "HEX": {
      "address": "0x2b591e99afe9f32eaa6214f7b7629768c40eeb39",
      "priceChanges": {
        "h24": -8.58375,
        "d7": -16.72014,
        "d30": -20.60312,
        "d60": -40.1671,
        "d90": -53.82154,
        "d200": -53.82154,
        "d1y": -80.43555
      }
    },
    "EHEX": {
      "address": "0x57fde0a71132198bbec939b98976993d8d89d225",
      "priceChanges": {
        "h24": -5.7411,
        "d7": -17.13486,
        "d30": -20.6277,
        "d60": -28.7094,
        "d90": -52.5768,
        "d200": -52.5768,
        "d1y": -66.1524
      }
    }
  }
}