{
  "lastUpdated": "2026-01-18T03:20:15.454Z",
  "PTGC": {
    "volume": {
      "vol7d": 301167.52863284334,
      "vol30d": 1371584.7650102177,
      "vol90d": 5425003.034711217
    },
    "liquidity": 2530899.2822999996,
    "transactions": {
      "buys": 196,
      "sells": 138,
      "total": 334,
      "buyVolume": 8425.471784927857,
      "sellVolume": 9117.784792215145
    },
    "holders": 17013,
    "tokensInLP": 9864105804.78,
    "poolCount": 20
  },
  "UFO": {
    "volume": {
      "vol7d": 31414.375234563886,
      "vol30d": 309168.37769383745,
      "vol90d": 1743912.0559507378
    },
    "liquidity": 2431198.5344,
    "transactions": {
      "buys": 49,
      "sells": 33,
      "total": 82,
      "buyVolume": 366.8994006383713,
      "sellVolume": 247.97976155808126
    },
    "holders": 6334,
    "tokensInLP": 177006825240,
    "poolCount": 20
  }
}