{
  "lastUpdated": "2026-01-16T04:56:16.242Z",
  "PTGC": {
    "volume": {
      "vol7d": 338822.6882754343,
      "vol30d": 1377712.6615790504,
      "vol90d": 5512676.830204849
    },
    "liquidity": 2567671.6527,
    "transactions": {
      "buys": 613,
      "sells": 345,
      "total": 958,
      "buyVolume": 25935.118449496702,
      "sellVolume": 47185.09898012885
    },
    "holders": 17012,
    "tokensInLP": 9910778714,
    "poolCount": 20
  },
  "UFO": {
    "volume": {
      "vol7d": 41671.556456316044,
      "vol30d": 294215.8598761786,
      "vol90d": 1714718.498932748
    },
    "liquidity": 2286033.0688999994,
    "transactions": {
      "buys": 68,
      "sells": 55,
      "total": 123,
      "buyVolume": 1081.7312874819188,
      "sellVolume": 717.2081294274568
    },
    "holders": 6335,
    "tokensInLP": 167048251455,
    "poolCount": 20
  }
}