{
  "lastUpdated": "2026-01-21T13:41:20.003Z",
  "PTGC": {
    "volume": {
      "vol7d": 249277.98597742803,
      "vol30d": 1401467.6446982438,
      "vol90d": 5370877.505256191
    },
    "liquidity": 2250594.6191,
    "transactions": {
      "buys": 320,
      "sells": 256,
      "total": 576,
      "buyVolume": 21889.4978938568,
      "sellVolume": 28541.99210035187
    },
    "holders": 17025,
    "tokensInLP": 9786686717.8811,
    "poolCount": 20,
    "priceChanges": {
      "h24": -3.38614,
      "d7": -18.64512,
      "d30": 3.49961,
      "d60": 22.6235,
      "d90": -55.47669,
      "d200": -55.47669,
      "d1y": -80.4695
    }
  },
  "UFO": {
    "volume": {
      "vol7d": 34669.30807941782,
      "vol30d": 332987.3891644982,
      "vol90d": 2055867.3471549843
    },
    "liquidity": 2624231.781600001,
    "transactions": {
      "buys": 70,
      "sells": 26,
      "total": 96,
      "buyVolume": 1612.051434745077,
      "sellVolume": 215.7847865661971
    },
    "holders": 6337,
    "tokensInLP": 218295667448,
    "poolCount": 20,
    "priceChanges": {
      "h24": 1.09652,
      "d7": -12.7953,
      "d30": -9.28983,
      "d60": -18.38174,
      "d90": -60.21224,
      "d200": -60.21224,
      "d1y": -90.07595
    }
  },
  "rhCores": {
    "WPLS": {
      "address": "0xa1077a294dde1b09bb078844df40758a5d0f9a27",
      "priceChanges": {
        "h24": 0.39616,
        "d7": -9.92396,
        "d30": -11.19779,
        "d60": -18.63168,
        "d90": -38.59761,
        "d200": -38.59761,
        "d1y": -70.73434
      }
    },
    "PLSX": {
      "address": "0x95b303987a60c71504d99aa1b13b4da07b0790ab",
      "priceChanges": {
        "h24": 0.96563,
        "d7": -12.32445,
        "d30": -14.13521,
        "d60": -1.11719,
        "d90": -34.46912,
        "d200": -34.46912,
        "d1y": -66.62686
      }
    },
    "INC": {
      "address": "0x2fa878ab3f87cc1c9737fc071108f904c0b0c95d",
      "priceChanges": {
        "h24": 2.14215,
        "d7": -9.79008,
        "d30": -9.93838,
        "d60": -21.66326,
        "d90": -59.22189,
        "d200": -59.22189,
        "d1y": -69.19841
      }
    },
    "HEX": {
      "address": "0x2b591e99afe9f32eaa6214f7b7629768c40eeb39",
      "priceChanges": {
        "h24": 2.01017,
        "d7": -15.23307,
        "d30": -15.89476,
        "d60": -35.94773,
        "d90": -54.06596,
        "d200": -54.06596,
        "d1y": -82.78595
      }
    },
    "EHEX": {
      "address": "0x57fde0a71132198bbec939b98976993d8d89d225",
      "priceChanges": {
        "h24": 0.32611,
        "d7": -11.47473,
        "d30": -12.1104,
        "d60": -25.78364,
        "d90": -52.14031,
        "d200": -52.14031,
        "d1y": -73.54042
      }
    }
  }
}