{
  "lastUpdated": "2026-01-29T05:03:15.656Z",
  "PTGC": {
    "volume": {
      "vol7d": 270737.5644945846,
      "vol30d": 1333805.8479045173,
      "vol90d": 5005086.312048796
    },
    "liquidity": 1850870.7253999999,
    "transactions": {
      "buys": 265,
      "sells": 149,
      "total": 414,
      "buyVolume": 17299.70741266265,
      "sellVolume": 21368.44724674764
    },
    "holders": 17051,
    "tokensInLP": 10303461049.009497,
    "poolCount": 20,
    "priceChanges": {
      "h24": -4.41788,
      "d7": -19.1025,
      "d30": 9.83194,
      "d60": -2.89347,
      "d90": -75.17929,
      "d200": -75.17929,
      "d1y": -87.72542
    }
  },
  "UFO": {
    "volume": {
      "vol7d": 133874.72693556396,
      "vol30d": 330156.2478369523,
      "vol90d": 1527833.5718885523
    },
    "liquidity": 1840835.6231,
    "transactions": {
      "buys": 74,
      "sells": 53,
      "total": 127,
      "buyVolume": 5295.818577562984,
      "sellVolume": 3936.6269123735856
    },
    "holders": 6333,
    "tokensInLP": 172296035275.8653,
    "poolCount": 20,
    "priceChanges": {
      "h24": -0.60224,
      "d7": -11.72431,
      "d30": -0.7023,
      "d60": -27.1852,
      "d90": -72.57859,
      "d200": -72.57859,
      "d1y": -93.94397
    }
  },
  "rhCores": {
    "WPLS": {
      "address": "0xa1077a294dde1b09bb078844df40758a5d0f9a27",
      "priceChanges": {
        "h24": -2.4081,
        "d7": -9.4082,
        "d30": -0.7798,
        "d60": -28.47286,
        "d90": -55.28074,
        "d200": -55.28074,
        "d1y": -73.44221
      }
    },
    "PLSX": {
      "address": "0x95b303987a60c71504d99aa1b13b4da07b0790ab",
      "priceChanges": {
        "h24": -3.40941,
        "d7": -5.1535,
        "d30": -5.24314,
        "d60": -8.17264,
        "d90": -50.95532,
        "d200": -50.95532,
        "d1y": -68.54923
      }
    },
    "INC": {
      "address": "0x2fa878ab3f87cc1c9737fc071108f904c0b0c95d",
      "priceChanges": {
        "h24": -3.55417,
        "d7": -9.71113,
        "d30": -17.01881,
        "d60": -20.54807,
        "d90": -66.02646,
        "d200": -66.02646,
        "d1y": -70.01357
      }
    },
    "HEX": {
      "address": "0x2b591e99afe9f32eaa6214f7b7629768c40eeb39",
      "priceChanges": {
        "h24": -3.86922,
        "d7": -13.92561,
        "d30": -7.41154,
        "d60": -39.71175,
        "d90": -59.18934,
        "d200": -59.18934,
        "d1y": -84.5723
      }
    },
    "EHEX": {
      "address": "0x57fde0a71132198bbec939b98976993d8d89d225",
      "priceChanges": {
        "h24": -2.25956,
        "d7": -11.01338,
        "d30": -11.45009,
        "d60": -32.6597,
        "d90": -56.80787,
        "d200": -56.80787,
        "d1y": -73.85336
      }
    }
  }
}