{
  "lastUpdated": "2026-01-14T20:16:56.775Z",
  "snapshots": [
    {
      "timestamp": "2026-01-14T19:51:01.534Z",
      "PTGC": {
        "buys": 522,
        "sells": 333,
        "total": 855,
        "buyVolume": 22259.184328267685,
        "sellVolume": 23611.79264705088
      },
      "UFO": {
        "buys": 97,
        "sells": 67,
        "total": 164,
        "buyVolume": 5354.2685561923345,
        "sellVolume": 5119.6508724702035
      }
    },
    {
      "timestamp": "2026-01-14T20:16:56.775Z",
      "PTGC": {
        "buys": 516,
        "sells": 323,
        "total": 839,
        "buyVolume": 20949.047941758312,
        "sellVolume": 19881.20880604341
      },
      "UFO": {
        "buys": 92,
        "sells": 69,
        "total": 161,
        "buyVolume": 4546.5434057684215,
        "sellVolume": 5328.141500953482
      }
    }
  ]
}